wop_pidfile/__init__.py
wop_pidfile-2.0.0.dist-info/METADATA
wop_pidfile-2.0.0.dist-info/WHEEL
wop_pidfile-2.0.0.dist-info/licenses/LICENSE
wop_pidfile-2.0.0.dist-info/RECORD
