Metadata-Version: 2.1
Name: wop_pidfile
Version: 2.0.0
Summary: Writes the process ID of the running Python process to the PID-file. If a pidfile exists it kills the running process if wanted.
Project-URL: Homepage, https://github.com/wopwopwopwopwop/wop_pidfile
Author: wopwopwopwopwop
License: Copyright (c) 2022 wopwopwopwopwop
License-File: LICENSE
Classifier: License :: OSI Approved :: MIT License
Classifier: Operating System :: OS Independent
Classifier: Programming Language :: Python :: 3
Requires-Python: >=3.7.0
